{
  "id": "237",
  "title": "Chapitre 237",
  "text": "Vous parvenez seulement à faire huit kilomètres vers le sud avant que l'Interceptor ne se trouve enlisée. Vous faites tourner les roues qui envoient des nuages de sable dans les airs, mais vous ne réussissez qu'à ensabler l'Interceptor un peu plus profondément. Vous maudissez votre sort mais vous n'avez aucune chance de vous sortir de là sans aide extérieure. Vous essayez bien de creuser sous les roues, mais c'est peine perdue et, découragé, vous vous rendez compte que vous allez devoir abandonner l'Interceptor. Avec un peu de chance, vous pourrez rejoindre Nouvelle Espérance et de là, faire une nouvelle tentative pour atteindre San Angelo.",
  "image": "/images/chap1.jpg",
  "choices": []
}
